{
  "projects": [
    {
      "visible": true,
      "category": "@ MICROSOFT",
      "title": "Microsoft Viva Engage: new Articles feature",
      "description": "I was one of two backend engineers on a feature crew that developed a brand-new post type from scratch — Articles, publicly released in March 2024.",
      "tags": ["General Availability", "Java", "GraphQL", "RFC Authoring & Review", "Microsoft Viva Engage"],
      "image": {
        "src": "../../images/viva-engage-articles.png",
        "alt": "Microsoft Viva Engage: new Articles feature",
        "linkTo": "https://techcommunity.microsoft.com/t5/viva-engage-blog/articles-now-available-in-viva-engage/ba-p/4070877"
      },
      "links": [
        {
          "type": "external",
          "url": "https://techcommunity.microsoft.com/t5/viva-engage-blog/articles-now-available-in-viva-engage/ba-p/4070877"
        }
      ]
    },
    {
      "visible": true,
      "category": "@ MICROSOFT",
      "title": "Microsoft Viva Engage: Copilot impression discounting",
      "description": "Built the backend implementation for impression discounting for Viva Engage Copilot's conversation starters, from firing the 'starter served' event from the UI down to database-level per-user tracking.",
      "tags": ["Copilot", "Recommender Systems", "Kafka", "Distributed Systems", "Microsoft Viva Engage"],
      "image": {
        "src": "../../images/viva-engage-copilot.png",
        "alt": "Microsoft Viva Engage: Copilot impression discounting"
      },
      "links": [
        {
          "type": "external",
          "url": "https://techcommunity.microsoft.com/t5/viva-engage-blog/announcing-copilot-in-viva-engage/ba-p/3771323"
        }
      ]
    },
    {
      "visible": true,
      "category": "PERSONAL",
      "title": "Spotify Open Recommendation Engine",
      "description": "the whole kit and kaboodle",
      "tags": ["Spotify API", "Project Management"],
      "image": {
        "src": "../../images/kelly-sikkema-Hl3LUdyKRic-unsplash.jpg",
        "alt": "Spotify Open Recommendation Engine"
      },
      "links": [
        {
          "type": "external",
          "url": "https://github.com/Spotify-Open-Recommendation-Engine/spotify-open-recommendation-engine"
        }
      ]
    }
  ],
  "button": {
    "visible": true,
    "label": "this is a button",
    "url": "https://kellyfesler.com/eden"
  }
}
